README.txt
setup.py
ia870/__init__.py
ia870/iaNlut.py
ia870/iaadd4dil.py
ia870/iaaddm.py
ia870/iaareaclose.py
ia870/iaareaopen.py
ia870/iaasf.py
ia870/iaasfrec.py
ia870/iabinary.py
ia870/iablob.py
ia870/iabshow.py
ia870/iacbisector.py
ia870/iacdil.py
ia870/iacenter.py
ia870/iacero.py
ia870/iaclohole.py
ia870/iaclose.py
ia870/iacloserec.py
ia870/iacloserecth.py
ia870/iacloseth.py
ia870/iacmp.py
ia870/iaconcat.py
ia870/iacthick.py
ia870/iacthin.py
ia870/iacwatershed.py
ia870/iadil.py
ia870/iadist.py
ia870/iadrawv.py
ia870/iaedgeoff.py
ia870/iaendpoints.py
ia870/iaero.py
ia870/iaframe.py
ia870/iagdist.py
ia870/iagdtshow.py
ia870/iaglblshow.py
ia870/iagplot.py
ia870/iagradm.py
ia870/iagrain.py
ia870/iagray.py
ia870/iagshow.py
ia870/iagsurf.py
ia870/iahmax.py
ia870/iahmin.py
ia870/iahomothick.py
ia870/iahomothin.py
ia870/iaimg2se.py
ia870/iainfcanon.py
ia870/iainfgen.py
ia870/iainfrec.py
ia870/iainpos.py
ia870/iainterot.py
ia870/iaintersec.py
ia870/iaintershow.py
ia870/iais.py
ia870/iaisbinary.py
ia870/iaisequal.py
ia870/iaislesseq.py
ia870/ialabel.py
ia870/ialabelflat.py
ia870/ialastero.py
ia870/ialimits.py
ia870/iamat2set.py
ia870/iamaxleveltype.py
ia870/ianeg.py
ia870/iaopen.py
ia870/iaopenrec.py
ia870/iaopenrecth.py
ia870/iaopenth.py
ia870/iaopentransf.py
ia870/iapad.py
ia870/iapad4n.py
ia870/iapatspec.py
ia870/iaregmax.py
ia870/iaregmin.py
ia870/iase2hmt.py
ia870/iase2interval.py
ia870/iase2off.py
ia870/iasebox.py
ia870/iasecrop.py
ia870/iasecross.py
ia870/iasedil.py
ia870/iasedisk.py
ia870/iaseintersec.py
ia870/iaseline.py
ia870/iasereflect.py
ia870/iaserot.py
ia870/iaseshow.py
ia870/iasesum.py
ia870/iaset2mat.py
ia870/iasetrans.py
ia870/iaseunion.py
ia870/iaskelm.py
ia870/iaskelmrec.py
ia870/iastats.py
ia870/iasubm.py
ia870/iasupcanon.py
ia870/iasupgen.py
ia870/iasuprec.py
ia870/iasymdif.py
ia870/iatext.py
ia870/iathick.py
ia870/iathin.py
ia870/iathreshad.py
ia870/iatoggle.py
ia870/iatz.py
ia870/iaunion.py
ia870/iaunpad.py
ia870/iawatershed.py
ia870/ipdp.py
ia870.egg-info/PKG-INFO
ia870.egg-info/SOURCES.txt
ia870.egg-info/dependency_links.txt
ia870.egg-info/top_level.txt