Metadata-Version: 1.1
Name: ia870
Version: 0.7
Summary: Python Morphology Toolbox for Teaching Image Processing
Home-page: https://github.com/robertoalotufo/ia870
Author: Roberto A Lotufo and collaborators
Author-email: robertoalotufo@gmail.com
License: BSD 3 clauses
Keywords: image processing,morphological image processing,mathematical morphology
Platform: UNKNOWN
Classifier: Development Status :: 4 - Beta
Classifier: Intended Audience :: Science/Research
Classifier: Programming Language :: Python :: 2 :: Only
Classifier: Topic :: Scientific/Engineering :: Image Recognition
Classifier: License :: OSI Approved :: BSD License
